py3_rest_shell-0.3.dist-info/METADATA
py3_rest_shell-0.3.dist-info/RECORD
py3_rest_shell-0.3.dist-info/WHEEL
py3_rest_shell-0.3.dist-info/entry_points.txt
py3_rest_shell-0.3.dist-info/top_level.txt
rest_shell/__init__.py
